deepdefacer/__init__.py
deepdefacer/defacer.py
deepdefacer/defacer_utils.py
deepdefacer-1.1.9.dist-info/LICENSE
deepdefacer-1.1.9.dist-info/METADATA
deepdefacer-1.1.9.dist-info/WHEEL
deepdefacer-1.1.9.dist-info/entry_points.txt
deepdefacer-1.1.9.dist-info/top_level.txt
deepdefacer-1.1.9.dist-info/RECORD
