Metadata-Version: 2.1
Name: deepdefacer
Version: 1.1.9
Summary: Automatic Removal of Facial Features from MRI Images
Home-page: https://github.com/AKhazane/DeepDeface
Author: Anish Khazane
Author-email: akhazane@stanford.edu
License: UNKNOWN
Download-URL: https://github.com/AKhazane/DeepDeface/archive/v_01.tar.gz
Platform: UNKNOWN
Classifier: Programming Language :: Python :: 2
Classifier: License :: OSI Approved :: MIT License
Classifier: Operating System :: OS Independent
Requires-Dist: numpy
Requires-Dist: keras
Requires-Dist: nilearn
Requires-Dist: nibabel
Requires-Dist: sklearn
Requires-Dist: scipy
Requires-Dist: ipython
Requires-Dist: matplotlib
Requires-Dist: SimpleITK
Provides-Extra: tf
Requires-Dist: tensorflow (>=1.8.0) ; extra == 'tf'
Provides-Extra: tf_gpu
Requires-Dist: tensorflow-gpu (>=1.0.0) ; extra == 'tf_gpu'
